dxchange/__init__.py
dxchange/_nbdev.py
dxchange/core.py
dxchange-0.0.1.dist-info/LICENSE
dxchange-0.0.1.dist-info/METADATA
dxchange-0.0.1.dist-info/WHEEL
dxchange-0.0.1.dist-info/entry_points.txt
dxchange-0.0.1.dist-info/top_level.txt
dxchange-0.0.1.dist-info/RECORD
