Metadata-Version: 2.1
Name: dxchange
Version: 0.0.1
Summary: The real data valuation and exchange library
Home-page: https://github.com/dwddao/dxchange/tree/master/
Author: David Dao
Author-email: dwddao@gmail.com
License: Apache Software License 2.0
Keywords: data valuation market
Platform: UNKNOWN
Classifier: Development Status :: 3 - Alpha
Classifier: Intended Audience :: Developers
Classifier: License :: OSI Approved :: Apache Software License
Classifier: Natural Language :: English
Classifier: Programming Language :: Python :: 3.6
Classifier: Programming Language :: Python :: 3.7
Classifier: Programming Language :: Python :: 3.8
Requires-Python: >=3.6
Requires-Dist: fastcore
